ratuil/__init__.py
ratuil/ansiscreen.py
ratuil/basescreen.py
ratuil/boxstyle.py
ratuil/bufferedscreen.py
ratuil/constants.py
ratuil/cursedpad.py
ratuil/cursedscreen.py
ratuil/drawtarget.py
ratuil/inputs.py
ratuil/layout.py
ratuil/pad.py
ratuil/screen.py
ratuil/screenelement.py
ratuil/strwidth.py
ratuil/textstyle.py
ratuil/window.py
ratuil/widgets/__init__.py
ratuil/widgets/adapt.py
ratuil/widgets/bar.py
ratuil/widgets/border.py
ratuil/widgets/box.py
ratuil/widgets/empty.py
ratuil/widgets/field.py
ratuil/widgets/fill.py
ratuil/widgets/frame.py
ratuil/widgets/hbox.py
ratuil/widgets/layout.py
ratuil/widgets/listing.py
ratuil/widgets/log.py
ratuil/widgets/overlay.py
ratuil/widgets/splitbox.py
ratuil/widgets/switchbox.py
ratuil/widgets/textbox.py
ratuil/widgets/textinput.py
ratuil/widgets/vbox.py
ratuil-0.3.0.dist-info/LICENSE
ratuil-0.3.0.dist-info/METADATA
ratuil-0.3.0.dist-info/WHEEL
ratuil-0.3.0.dist-info/top_level.txt
ratuil-0.3.0.dist-info/RECORD
