Metadata-Version: 2.1
Name: ratuil
Version: 0.3.0
Summary: A terminal UI library for games
Home-page: https://github.com/jmdejong/ratuil
Author: troido
Author-email: troido@protonmail.com
License: UNKNOWN
Platform: UNKNOWN
Classifier: Programming Language :: Python :: 3
Classifier: License :: OSI Approved :: MIT License
Classifier: Operating System :: OS Independent
Requires-Python: >=3.6
